{
  "description": "EXPERIMENTAL frequency-tuned spec generated by the Aero optimizer. Sandbox-only artifact; do not promote into root config without a benchmark win.",
  "language": "aero",
  "version": 1,
  "keywords": [
    "let",
    "return",
    "fn",
    "if",
    "else",
    "while"
  ],
  "booleans": [
    "true",
    "false"
  ],
  "operators": [
    "<=",
    "==",
    "!=",
    ">=",
    "&&",
    "||",
    "+",
    "=",
    "-",
    "*",
    "/",
    "%",
    "<",
    ">",
    "!"
  ],
  "punctuation": [
    "(",
    ")",
    "{",
    "}",
    ",",
    ";"
  ],
  "preference_levels": {
    "==": 64,
    "!=": 62,
    "<=": 89,
    ">=": 3,
    "&&": 74,
    "||": 10,
    "+": 6,
    "-": 65,
    "*": 93,
    "/": 17,
    "%": 25,
    "=": 74,
    "<": 29,
    ">": 13,
    "!": 21
  },
  "custom_errors": {
    "@": "Unexpected character '@' - not a valid token",
    "#": "Unexpected character '#' - not a valid token",
    "$": "Unexpected character '$' - not a valid token",
    "~": "Unexpected character '~' - not a valid token",
    "`": "Unexpected character '`' - not a valid token"
  },
  "_evolution_epoch_timestamp": 1780506291226,
  "_evolution_iteration_round": 58,
  "_active_generation_seed": 224
}