{
  "description": "EXPERIMENTAL frequency-tuned spec generated by the Aero optimizer. Sandbox-only artifact; do not promote into root config without a benchmark win.",
  "language": "aero",
  "version": 1,
  "keywords": [
    "let",
    "return",
    "fn",
    "if",
    "else",
    "while"
  ],
  "booleans": [
    "true",
    "false"
  ],
  "operators": [
    "<=",
    "==",
    "!=",
    ">=",
    "&&",
    "||",
    "+",
    "=",
    "-",
    "*",
    "/",
    "%",
    "<",
    ">",
    "!"
  ],
  "punctuation": [
    "(",
    ")",
    "{",
    "}",
    ",",
    ";"
  ],
  "preference_levels": {
    "==": 70,
    "!=": 94,
    "<=": 96,
    ">=": 63,
    "&&": 71,
    "||": 36,
    "+": 60,
    "-": 69,
    "*": 14,
    "/": 36,
    "%": 62,
    "=": 90,
    "<": 46,
    ">": 97,
    "!": 39
  },
  "custom_errors": {
    "@": "Unexpected character '@' - not a valid token",
    "#": "Unexpected character '#' - not a valid token",
    "$": "Unexpected character '$' - not a valid token",
    "~": "Unexpected character '~' - not a valid token",
    "`": "Unexpected character '`' - not a valid token"
  },
  "_evolution_epoch_timestamp": 1780506016344,
  "_evolution_iteration_round": 12,
  "_active_generation_seed": 735
}