{
  "description": "EXPERIMENTAL frequency-tuned spec generated by the Aero optimizer. Sandbox-only artifact; do not promote into root config without a benchmark win.",
  "language": "aero",
  "version": 1,
  "keywords": [
    "let",
    "fn",
    "return",
    "else",
    "if",
    "while"
  ],
  "booleans": [
    "true",
    "false"
  ],
  "operators": [
    "<=",
    "==",
    "!=",
    ">=",
    "&&",
    "||",
    "=",
    "+",
    "*",
    "-",
    "/",
    "%",
    "<",
    ">",
    "!"
  ],
  "punctuation": [
    "(",
    ")",
    "{",
    "}",
    ",",
    ";"
  ],
  "preference_levels": {
    "<=": 38,
    "==": 97,
    "!=": 32,
    ">=": 69,
    "&&": 18,
    "||": 81,
    "+": 31,
    "=": 71,
    "-": 28,
    "*": 3,
    "/": 17,
    "%": 84,
    "<": 22,
    ">": 84,
    "!": 59
  },
  "custom_errors": {
    "@": "Unexpected character '@' - not a valid token",
    "#": "Unexpected character '#' - not a valid token",
    "$": "Unexpected character '$' - not a valid token",
    "~": "Unexpected character '~' - not a valid token",
    "`": "Unexpected character '`' - not a valid token"
  },
  "_evolution_epoch_timestamp": 1780510290583,
  "_evolution_iteration_round": 43,
  "_evolution_convergence_bypass": true
}