{
  "description": "EXPERIMENTAL frequency-tuned spec generated by the Aero optimizer. Sandbox-only artifact; do not promote into root config without a benchmark win.",
  "language": "aero",
  "version": 1,
  "keywords": [
    "let",
    "fn",
    "return",
    "else",
    "if",
    "while"
  ],
  "booleans": [
    "true",
    "false"
  ],
  "operators": [
    "&&",
    "||",
    "==",
    "<=",
    "!=",
    ">=",
    "=",
    "+",
    "*",
    "<",
    "-",
    "!",
    "%",
    "/",
    ">"
  ],
  "punctuation": [
    "(",
    ")",
    "{",
    "}",
    ",",
    ";"
  ],
  "preference_levels": {
    "<=": 4,
    "==": 5,
    "!=": 2,
    ">=": 0,
    "&&": 10,
    "||": 9,
    "+": 18,
    "=": 38,
    "-": 9,
    "*": 13,
    "/": 2,
    "%": 4,
    "<": 10,
    ">": 0,
    "!": 9
  },
  "custom_errors": {
    "@": "Unexpected character '@' - not a valid token",
    "#": "Unexpected character '#' - not a valid token",
    "$": "Unexpected character '$' - not a valid token",
    "~": "Unexpected character '~' - not a valid token",
    "`": "Unexpected character '`' - not a valid token"
  },
  "_evolution_epoch_timestamp": 1782565745227,
  "_evolution_iteration_round": 32,
  "_evolution_convergence_bypass": true
}